rich_text/__init__.py
rich_text/models.py
rich_text/templates/rich_text/rich-text.html
rich_text_package-0.0.1.dist-info/LICENSE
rich_text_package-0.0.1.dist-info/METADATA
rich_text_package-0.0.1.dist-info/WHEEL
rich_text_package-0.0.1.dist-info/top_level.txt
rich_text_package-0.0.1.dist-info/RECORD
