Metadata-Version: 2.1
Name: rich-text-package
Version: 0.0.1
Summary: Un package Django pour gérer du texte riche.
Home-page: https://gitlab.com/webissito/widgets/
Author: Alexandre PEPIN
Author-email: alexandre.pepin@webissito.fr
License: MIT
Classifier: Framework :: Django
Classifier: Programming Language :: Python :: 3
Classifier: License :: OSI Approved :: MIT License
License-File: LICENSE
